rdgc/__init__.py
rdgc/graph/__init__.py
rdgc/graph/base.py
rdgc/graph/connected.py
rdgc/graph/degree.py
rdgc/graph/tree.py
rdgc/graph/utils.py
rdgc/nt.py
rdgc/seq.py
rdgc/utils.py
rdgc-0.7.0.dist-info/METADATA
rdgc-0.7.0.dist-info/WHEEL
rdgc-0.7.0.dist-info/RECORD
